cdk_cloudformation_unxpose_iam_integration_module/__init__.py
cdk_cloudformation_unxpose_iam_integration_module/py.typed
cdk_cloudformation_unxpose_iam_integration_module/_jsii/__init__.py
cdk_cloudformation_unxpose_iam_integration_module/_jsii/unxpose-iam-integration-module@1.1.1-alpha.7.jsii.tgz
cdk_cloudformation_unxpose_iam_integration_module-1.1.1a7.dist-info/LICENSE
cdk_cloudformation_unxpose_iam_integration_module-1.1.1a7.dist-info/METADATA
cdk_cloudformation_unxpose_iam_integration_module-1.1.1a7.dist-info/WHEEL
cdk_cloudformation_unxpose_iam_integration_module-1.1.1a7.dist-info/top_level.txt
cdk_cloudformation_unxpose_iam_integration_module-1.1.1a7.dist-info/RECORD
